odoo9_addon_website_payment_v10-9.0.1.0.0.99.dev4-py2.7-nspkg.pth
odoo9_addon_website_payment_v10-9.0.1.0.0.99.dev4.dist-info/DESCRIPTION.rst
odoo9_addon_website_payment_v10-9.0.1.0.0.99.dev4.dist-info/METADATA
odoo9_addon_website_payment_v10-9.0.1.0.0.99.dev4.dist-info/RECORD
odoo9_addon_website_payment_v10-9.0.1.0.0.99.dev4.dist-info/WHEEL
odoo9_addon_website_payment_v10-9.0.1.0.0.99.dev4.dist-info/metadata.json
odoo9_addon_website_payment_v10-9.0.1.0.0.99.dev4.dist-info/namespace_packages.txt
odoo9_addon_website_payment_v10-9.0.1.0.0.99.dev4.dist-info/top_level.txt
odoo_addons/website_payment_v10/README.rst
odoo_addons/website_payment_v10/__init__.py
odoo_addons/website_payment_v10/__openerp__.py
odoo_addons/website_payment_v10/i18n/website_payment_v10.pot
odoo_addons/website_payment_v10/static/description/icon.png
odoo_addons/website_payment_v10/static/lib/jquery.payment/jquery.payment.js
odoo_addons/website_payment_v10/views/website_payment_templates.xml
