Metadata-Version: 2.0
Name: odoo9-addon-website-payment-v10
Version: 9.0.1.0.0.99.dev4
Summary: Payment: Website Integration
Home-page: UNKNOWN
Author: Odoo S.A.,Tecnativa,Odoo Community Association (OCA)
Author-email: support@odoo-community.org
License: UNKNOWN
Platform: UNKNOWN
Classifier: Programming Language :: Python
Classifier: Framework :: Odoo
Requires-Python: ~=2.7
Requires-Dist: odoo (<9.1a,>=9.0a)
Requires-Dist: odoo9-addon-website-portal-v10
